{
  "show-part-2": [
    {
      "status": "on",
      "color": "000000",
      "brightness": 100,
      "duration": 1000
    },
    {
      "status": "flash",
      "color": "0060ff",
      "brightness": 100,
      "duration": 4000,
      "random": 30,
      "flashInterval": 100
    },
    {
      "status": "flash",
      "color": "0060ff",
      "brightness": 100,
      "duration": 4000,
      "random": 70,
      "flashInterval": 100
    },
    {
      "status": "on",
      "color": "0060ff",
      "brightness": 100,
      "duration": 2000
    },
    {
      "status": "flash",
      "color": "0060ff",
      "brightness": 100,
      "duration": 3500,
      "flashInterval": 100
    },
    {
      "status": "on",
      "color": "000000",
      "brightness": 100,
      "duration": 1000
    },
    {
      "status": "flash",
      "color": "0060ff",
      "brightness": 100,
      "duration": 3500,
      "random": 30,
      "flashInterval": 500
    },
    {
      "status": "flash",
      "color": "0060ff",
      "brightness": 100,
      "duration": 3500,
      "random": 60,
      "flashInterval": 500
    },
    {
      "status": "on",
      "color": "0060ff",
      "brightness": 100,
      "duration": 3500
    },
    {
      "status": "flash",
      "color": "0060ff",
      "brightness": 100,
      "duration": 4500,
      "flashInterval": 100
    }
  ]
}

